README.md
setup.py
spirentapi/API.TXT
spirentapi/__init__.py
spirentapi/apiwrapper.py
spirentapi/object.py
spirentapi/tclwrapper.py
spirentapi/utils.py
spirentapi.egg-info/PKG-INFO
spirentapi.egg-info/SOURCES.txt
spirentapi.egg-info/dependency_links.txt
spirentapi.egg-info/requires.txt
spirentapi.egg-info/top_level.txt
test/test_spirentapi.py
test/test_stcobject.py