Metadata-Version: 2.1
Name: spirentapi
Version: 1.4.1
Summary: wrapper to the Spirent TestCenter Tcl shell API(stc::, sth::)
Home-page: https://github.com/dvdface/spirentapi
Author: Ding Yi
Author-email: dvdface@hotmail.com
License: MIT
Platform: UNKNOWN
Classifier: Programming Language :: Python :: 3
Classifier: License :: OSI Approved :: MIT License
Classifier: Operating System :: OS Independent
Requires-Python: >=3.6
